gemini_parallel/__init__.py
gemini_parallel/executor.py
gemini_parallel/mongo_logger.py
gemini_parallel/processors.py
gemini_parallel_mongodb-0.1.0.dist-info/METADATA
gemini_parallel_mongodb-0.1.0.dist-info/WHEEL
gemini_parallel_mongodb-0.1.0.dist-info/licenses/LICENSE
gemini_parallel_mongodb-0.1.0.dist-info/RECORD
