Metadata-Version: 2.4
Name: gemini-parallel-mongodb
Version: 0.1.0
Summary: Parallel Gemini API calls with MongoDB logging support
Project-URL: Homepage, https://github.com/miroblog/gemini-parallel
Project-URL: Repository, https://github.com/miroblog/gemini-parallel
Project-URL: Issues, https://github.com/miroblog/gemini-parallel/issues
Author-email: miroblog <miroblog@snu.ac.kr>
License: MIT
License-File: LICENSE
Keywords: ai,api,async,gemini,genai,mongodb,parallel
Classifier: Development Status :: 4 - Beta
Classifier: Intended Audience :: Developers
Classifier: License :: OSI Approved :: MIT License
Classifier: Programming Language :: Python :: 3
Classifier: Programming Language :: Python :: 3.8
Classifier: Programming Language :: Python :: 3.9
Classifier: Programming Language :: Python :: 3.10
Classifier: Programming Language :: Python :: 3.11
Classifier: Programming Language :: Python :: 3.12
Classifier: Topic :: Scientific/Engineering :: Artificial Intelligence
Classifier: Topic :: Software Development :: Libraries :: Python Modules
Requires-Python: >=3.8
Requires-Dist: google-genai>=1.36.0
Requires-Dist: motor>=3.7.1
Requires-Dist: pillow>=11.3.0
Requires-Dist: pydantic>=2.11.9
Requires-Dist: pymongo>=4.15.0
Requires-Dist: python-dotenv>=1.1.1
Requires-Dist: tqdm>=4.67.1
